whello/__init__.py
whello/api.py
whello-0.1.0.dist-info/WHEEL
whello-0.1.0.dist-info/METADATA
whello-0.1.0.dist-info/RECORD
