Metadata-Version: 2.1
Name: whello
Version: 0.1.0
Summary: 
Author: Wissem Mansouri
Author-email: wissem.mansouri.ing@gmail.com
Requires-Python: >=3.8
Classifier: Programming Language :: Python :: 3
Classifier: Programming Language :: Python :: 3.10
Classifier: Programming Language :: Python :: 3.8
Classifier: Programming Language :: Python :: 3.9
Requires-Dist: requests (>=2.26.0,<3.0.0)
